qc_benchmark_dwave/__init__.py
qc_benchmark_dwave/__version__.py
qc_benchmark_dwave/agent_api.py
qc_benchmark_dwave/dwave_leap.py
qc_benchmark_dwave/testing_client_json.py
qc_benchmark_dwave-1.1.dist-info/LICENSE
qc_benchmark_dwave-1.1.dist-info/METADATA
qc_benchmark_dwave-1.1.dist-info/WHEEL
qc_benchmark_dwave-1.1.dist-info/top_level.txt
qc_benchmark_dwave-1.1.dist-info/RECORD
