Metadata-Version: 2.1
Name: qc-benchmark-dwave
Version: 1.1
Summary: caict qc benchmark tooklit for Dwave Leap cloud
Home-page: https://gitee.com/lvboodvl/qc_benchmark.git
Author: CAICT-lvbo
Author-email: lvbo@caict.ac.cn
License: Apache
Platform: UNKNOWN
Classifier: Programming Language :: Python
Classifier: Programming Language :: Python :: 3
Classifier: Programming Language :: Python :: 3.6
Classifier: Programming Language :: Python :: Implementation :: CPython
Classifier: Programming Language :: Python :: Implementation :: PyPy
Requires-Python: >=3.6.0
License-File: LICENSE
Requires-Dist: absl-py (==0.12.0)
Requires-Dist: aliyun-python-sdk-core (==2.13.33)
Requires-Dist: aliyun-python-sdk-kms (==2.14.0)
Requires-Dist: argparse (==1.1)
Requires-Dist: argon2-cffi (==20.1.0)
Requires-Dist: asgiref (==3.3.4)
Requires-Dist: async-generator (==1.10)
Requires-Dist: attrs (==20.3.0)
Requires-Dist: backcall (==0.2.0)
Requires-Dist: bleach (==3.3.0)
Requires-Dist: certifi (==2020.12.5)
Requires-Dist: cffi (==1.14.5)
Requires-Dist: chardet (==4.0.0)
Requires-Dist: click (==7.1.2)
Requires-Dist: cprotobuf (==0.1.9)
Requires-Dist: crcmod (==1.7)
Requires-Dist: cryptography (==3.4.7)
Requires-Dist: cycler (==0.10.0)
Requires-Dist: decorator (==4.4.2)
Requires-Dist: defusedxml (==0.7.1)
Requires-Dist: Deprecated (==1.2.12)
Requires-Dist: dimod (==0.9.13)
Requires-Dist: dwave-cloud-client (==0.8.4)
Requires-Dist: dwave-drivers (==0.4.4)
Requires-Dist: dwave-greedy (==0.1.2)
Requires-Dist: dwave-hybrid (==0.6.1)
Requires-Dist: dwave-inspector (==0.2.5)
Requires-Dist: dwave-inspectorapp (==0.2.2)
Requires-Dist: dwave-neal (==0.5.7)
Requires-Dist: dwave-networkx (==0.8.8)
Requires-Dist: dwave-ocean-sdk (==3.3.0)
Requires-Dist: dwave-qbsolv (==0.3.2)
Requires-Dist: dwave-system (==1.4.0)
Requires-Dist: dwave-tabu (==0.3.1)
Requires-Dist: dwavebinarycsp (==0.1.2)
Requires-Dist: entrypoints (==0.3)
Requires-Dist: fastapi (==0.65.1)
Requires-Dist: fasteners (==0.16)
Requires-Dist: Flask (==1.1.2)
Requires-Dist: funcsigs (==1.0.2)
Requires-Dist: h11 (==0.12.0)
Requires-Dist: homebase (==1.0.1)
Requires-Dist: idna (==2.10)
Requires-Dist: importlib-resources (==5.1.2)
Requires-Dist: ipykernel (==5.5.3)
Requires-Dist: ipython (==7.22.0)
Requires-Dist: ipython-genutils (==0.2.0)
Requires-Dist: ipywidgets (==7.6.3)
Requires-Dist: itsdangerous (==1.1.0)
Requires-Dist: jedi (==0.18.0)
Requires-Dist: Jinja2 (==2.11.3)
Requires-Dist: jmespath (==0.10.0)
Requires-Dist: jsonschema (==3.2.0)
Requires-Dist: jupyter (==1.0.0)
Requires-Dist: jupyter-client (==6.1.12)
Requires-Dist: jupyter-console (==6.4.0)
Requires-Dist: jupyter-core (==4.7.1)
Requires-Dist: jupyterlab-pygments (==0.1.2)
Requires-Dist: jupyterlab-widgets (==1.0.0)
Requires-Dist: kiwisolver (==1.3.1)
Requires-Dist: lz4 (==3.1.3)
Requires-Dist: MarkupSafe (==1.1.1)
Requires-Dist: matplotlib (==3.4.1)
Requires-Dist: minorminer (==0.2.5)
Requires-Dist: mistune (==0.8.4)
Requires-Dist: nbclient (==0.5.3)
Requires-Dist: nbconvert (==6.0.7)
Requires-Dist: nbformat (==5.1.3)
Requires-Dist: nest-asyncio (==1.5.1)
Requires-Dist: networkx (==2.5.1)
Requires-Dist: notebook (==6.3.0)
Requires-Dist: ortools (==8.2.8710)
Requires-Dist: oss2 (==2.14.0)
Requires-Dist: packaging (==20.9)
Requires-Dist: pandas (==1.2.4)
Requires-Dist: pandocfilters (==1.4.3)
Requires-Dist: parso (==0.8.2)
Requires-Dist: penaltymodel (==0.16.4)
Requires-Dist: penaltymodel-cache (==0.4.3)
Requires-Dist: penaltymodel-lp (==0.1.4)
Requires-Dist: penaltymodel-mip (==0.2.4)
Requires-Dist: pexpect (==4.8.0)
Requires-Dist: pickleshare (==0.7.5)
Requires-Dist: Pillow (==8.2.0)
Requires-Dist: plucky (==0.4.3)
Requires-Dist: prometheus-client (==0.10.1)
Requires-Dist: prompt-toolkit (==3.0.18)
Requires-Dist: protobuf (==3.15.8)
Requires-Dist: ptyprocess (==0.7.0)
Requires-Dist: pycparser (==2.20)
Requires-Dist: pycryptodome (==3.10.1)
Requires-Dist: pydantic (==1.8.2)
Requires-Dist: pydatahub (==2.17.0)
Requires-Dist: Pygments (==2.8.1)
Requires-Dist: pyparsing (==2.4.7)
Requires-Dist: pyqubo (==1.0.10)
Requires-Dist: pyrsistent (==0.17.3)
Requires-Dist: PySocks (==1.7.1)
Requires-Dist: python-dateutil (==2.8.1)
Requires-Dist: pytz (==2021.1)
Requires-Dist: pyzmq (==22.0.3)
Requires-Dist: qtconsole (==5.0.3)
Requires-Dist: QtPy (==1.9.0)
Requires-Dist: requests (==2.25.1)
Requires-Dist: scipy (==1.6.2)
Requires-Dist: Send2Trash (==1.5.0)
Requires-Dist: simplejson (==3.17.2)
Requires-Dist: six (==1.15.0)
Requires-Dist: starlette (==0.14.2)
Requires-Dist: terminado (==0.9.4)
Requires-Dist: testpath (==0.4.4)
Requires-Dist: tornado (==6.1)
Requires-Dist: traitlets (==5.0.5)
Requires-Dist: typing-extensions (==3.10.0.0)
Requires-Dist: urllib3 (==1.26.4)
Requires-Dist: uvicorn (==0.14.0)
Requires-Dist: wcwidth (==0.2.5)
Requires-Dist: webencodings (==0.5.1)
Requires-Dist: Werkzeug (==1.0.1)
Requires-Dist: widgetsnbextension (==3.5.1)
Requires-Dist: wrapt (==1.12.1)
